pipecat_ai_flows-0.0.21.dist-info/licenses/LICENSE
pipecat_flows/__init__.py
pipecat_flows/actions.py
pipecat_flows/adapters.py
pipecat_flows/exceptions.py
pipecat_flows/manager.py
pipecat_flows/types.py
pipecat_ai_flows-0.0.21.dist-info/METADATA
pipecat_ai_flows-0.0.21.dist-info/WHEEL
pipecat_ai_flows-0.0.21.dist-info/top_level.txt
pipecat_ai_flows-0.0.21.dist-info/RECORD
