Metadata-Version: 2.4
Name: pipecat-ai-flows
Version: 0.0.21
Summary: Conversation Flow management for Pipecat AI applications
License: BSD 2-Clause License
Project-URL: Source, https://github.com/pipecat-ai/pipecat-flows
Project-URL: Website, https://www.pipecat.ai
Keywords: pipecat,conversation,flows,state machine,ai,llm
Classifier: Development Status :: 4 - Beta
Classifier: Intended Audience :: Developers
Classifier: License :: OSI Approved :: BSD License
Classifier: Topic :: Scientific/Engineering :: Artificial Intelligence
Classifier: Topic :: Communications :: Conferencing
Classifier: Topic :: Multimedia :: Sound/Audio
Requires-Python: >=3.10
License-File: LICENSE
Requires-Dist: pipecat-ai>=0.0.85
Requires-Dist: loguru~=0.7.2
Requires-Dist: docstring_parser~=0.16
Dynamic: license-file
